autograde_visualizer/__init__.py
autograde_visualizer/frontend/build/asset-manifest.json
autograde_visualizer/frontend/build/bootstrap.min.css
autograde_visualizer/frontend/build/index.html
autograde_visualizer/frontend/build/precache-manifest.31e29a090970db3849d85af155315494.js
autograde_visualizer/frontend/build/precache-manifest.373145542e6b1b1d82611afe78685c7c.js
autograde_visualizer/frontend/build/precache-manifest.3f8d79b56e718a77dced4616761a1770.js
autograde_visualizer/frontend/build/service-worker.js
autograde_visualizer/frontend/build/static/js/2.f672bc8f.chunk.js
autograde_visualizer/frontend/build/static/js/2.f672bc8f.chunk.js.LICENSE.txt
autograde_visualizer/frontend/build/static/js/2.f672bc8f.chunk.js.map
autograde_visualizer/frontend/build/static/js/main.40eec251.chunk.js
autograde_visualizer/frontend/build/static/js/main.40eec251.chunk.js.map
autograde_visualizer/frontend/build/static/js/main.955d15c8.chunk.js
autograde_visualizer/frontend/build/static/js/main.955d15c8.chunk.js.map
autograde_visualizer/frontend/build/static/js/main.f7db1278.chunk.js
autograde_visualizer/frontend/build/static/js/main.f7db1278.chunk.js.map
autograde_visualizer/frontend/build/static/js/runtime-main.e4cdaade.js
autograde_visualizer/frontend/build/static/js/runtime-main.e4cdaade.js.map
autograde_visualizer-0.0.24.dist-info/LICENSE
autograde_visualizer-0.0.24.dist-info/METADATA
autograde_visualizer-0.0.24.dist-info/WHEEL
autograde_visualizer-0.0.24.dist-info/top_level.txt
autograde_visualizer-0.0.24.dist-info/RECORD
