Metadata-Version: 2.1
Name: autograde-visualizer
Version: 0.0.24
Home-page: 
Author: 
Author-email: 
Requires-Python: >=3.6
License-File: LICENSE
Requires-Dist: streamlit (>=0.63)
